alam1083/__init__.py
alam1083/geometry.py
alam1083/matrix.py
my_package/__init__.py
my_package/geometry.py
my_package/matrix.py
alam1083-0.1.dist-info/METADATA
alam1083-0.1.dist-info/WHEEL
alam1083-0.1.dist-info/top_level.txt
alam1083-0.1.dist-info/RECORD
