Metadata-Version: 2.1
Name: alam1083
Version: 0.1
Summary: A simple calculator and logger package
Author: Ahmad Mahbubul alam
Author-email: amahbubul85@gmail.com
Classifier: Programming Language :: Python :: 3
Classifier: Operating System :: OS Independent
Requires-Python: >=3.6
